odoo/addons/module_analysis/README.rst
odoo/addons/module_analysis/__init__.py
odoo/addons/module_analysis/__manifest__.py
odoo/addons/module_analysis/data/ir_config_parameter.xml
odoo/addons/module_analysis/data/ir_cron.xml
odoo/addons/module_analysis/data/ir_module_type.xml
odoo/addons/module_analysis/data/ir_module_type_rule.xml
odoo/addons/module_analysis/i18n/es.po
odoo/addons/module_analysis/i18n/it.po
odoo/addons/module_analysis/i18n/module_analysis.pot
odoo/addons/module_analysis/i18n/zh_CN.po
odoo/addons/module_analysis/models/__init__.py
odoo/addons/module_analysis/models/ir_module_author.py
odoo/addons/module_analysis/models/ir_module_module.py
odoo/addons/module_analysis/models/ir_module_type.py
odoo/addons/module_analysis/models/ir_module_type_rule.py
odoo/addons/module_analysis/readme/CONFIGURE.md
odoo/addons/module_analysis/readme/CONTRIBUTORS.md
odoo/addons/module_analysis/readme/DESCRIPTION.md
odoo/addons/module_analysis/readme/INSTALL.md
odoo/addons/module_analysis/readme/USAGE.md
odoo/addons/module_analysis/security/ir.model.access.csv
odoo/addons/module_analysis/static/description/add_module_type_rules.png
odoo/addons/module_analysis/static/description/analysis_pie.png
odoo/addons/module_analysis/static/description/analysis_pivot.png
odoo/addons/module_analysis/static/description/config_parameters.png
odoo/addons/module_analysis/static/description/default_module_type_rules.png
odoo/addons/module_analysis/static/description/icon.png
odoo/addons/module_analysis/static/description/index.html
odoo/addons/module_analysis/static/description/installed_modules_by_types.png
odoo/addons/module_analysis/static/description/module_authors.png
odoo/addons/module_analysis/static/description/module_form.png
odoo/addons/module_analysis/static/description/module_types.png
odoo/addons/module_analysis/tests/__init__.py
odoo/addons/module_analysis/tests/test_module.py
odoo/addons/module_analysis/views/menu.xml
odoo_addon_module_analysis-18.0.1.0.0.2.dist-info/METADATA
odoo_addon_module_analysis-18.0.1.0.0.2.dist-info/WHEEL
odoo_addon_module_analysis-18.0.1.0.0.2.dist-info/top_level.txt
odoo_addon_module_analysis-18.0.1.0.0.2.dist-info/RECORD
