Metadata-Version: 2.1
Name: odoo-addon-module_analysis
Version: 18.0.1.0.0.2
Requires-Python: >=3.10
Requires-Dist: odoo==18.0.*
Requires-Dist: pygount
Summary: Add analysis tools regarding installed modules to know which installed modules comes from Odoo Core, OCA, or are custom modules
Home-page: https://github.com/OCA/server-tools
License: AGPL-3
Author: GRAP, Odoo Community Association (OCA)
Author-email: support@odoo-community.org
Classifier: Programming Language :: Python
Classifier: Framework :: Odoo
Classifier: Framework :: Odoo :: 18.0
Classifier: License :: OSI Approved :: GNU Affero General Public License v3
